airbrowser_client/__init__.py
airbrowser_client/api_client.py
airbrowser_client/api_response.py
airbrowser_client/configuration.py
airbrowser_client/exceptions.py
airbrowser_client/py.typed
airbrowser_client/rest.py
airbrowser_client/api/__init__.py
airbrowser_client/api/auto_browser_api.py
airbrowser_client/api/browser_api.py
airbrowser_client/api/health_api.py
airbrowser_client/api/pool_api.py
airbrowser_client/api/profiles_api.py
airbrowser_client/models/__init__.py
airbrowser_client/models/action_result.py
airbrowser_client/models/attribute_response.py
airbrowser_client/models/base_response.py
airbrowser_client/models/browser_config.py
airbrowser_client/models/browser_created.py
airbrowser_client/models/browser_creation_data.py
airbrowser_client/models/browser_info_response.py
airbrowser_client/models/browser_list.py
airbrowser_client/models/browser_list_data.py
airbrowser_client/models/browsers_request.py
airbrowser_client/models/check_element_request.py
airbrowser_client/models/click_request.py
airbrowser_client/models/combined_dialog_request.py
airbrowser_client/models/combined_emulate_request.py
airbrowser_client/models/combined_gui_click_request.py
airbrowser_client/models/combined_scroll_request.py
airbrowser_client/models/console_logs_request.py
airbrowser_client/models/content_data.py
airbrowser_client/models/content_response.py
airbrowser_client/models/cookies_request.py
airbrowser_client/models/create_browser_request.py
airbrowser_client/models/create_profile_request.py
airbrowser_client/models/detect_coordinates_request.py
airbrowser_client/models/detect_coordinates_result.py
airbrowser_client/models/dialog_request.py
airbrowser_client/models/element_data_request.py
airbrowser_client/models/emulate_request.py
airbrowser_client/models/error_response.py
airbrowser_client/models/execute_cdp_request.py
airbrowser_client/models/execute_data.py
airbrowser_client/models/execute_request.py
airbrowser_client/models/execute_response.py
airbrowser_client-1.13.0.dist-info/METADATA
airbrowser_client-1.13.0.dist-info/WHEEL
airbrowser_client-1.13.0.dist-info/top_level.txt
airbrowser_client-1.13.0.dist-info/RECORD
